main.py
PyAudioCensor-0.0.1.dist-info/LICENSE.txt
PyAudioCensor-0.0.1.dist-info/METADATA
PyAudioCensor-0.0.1.dist-info/WHEEL
PyAudioCensor-0.0.1.dist-info/top_level.txt
PyAudioCensor-0.0.1.dist-info/RECORD
