Metadata-Version: 2.1
Name: PyAudioCensor
Version: 0.0.1
Summary: Automated Offline Censoring of Audio Files using Vosk and Python.
Author: Mayukhmali Das
Requires-Python: >=3.6
License-File: LICENSE.txt
